nvdsw/LICENSE
nvdsw/__init__.py
nvdsw/_version.py
nvdsw/main.py
nvdsw/setup.py
nvdsw/config/config.ini
nvdsw/config/menus.yaml
nvdsw/config/usersettings.yaml
nvdsw/docker/nvdsw_deepstream/Dockerfile.5.1
nvdsw/docker/nvdsw_deepstream/Dockerfile.6.0
nvdsw/docker/nvdsw_dss/Dockerfile.2.9.0
nvdsw/docker/nvdsw_kaggle/Dockerfile.101
nvdsw/docker/nvdsw_kaggle/Dockerfile.102
nvdsw/docker/nvdsw_kaggle/Dockerfile.103
nvdsw/docker/nvdsw_kaggle/Dockerfile.104
nvdsw/docker/nvdsw_kaggle/Dockerfile.105
nvdsw/docker/nvdsw_kaggle/Dockerfile.106
nvdsw/docker/nvdsw_kaggle/Dockerfile.107
nvdsw/docker/nvdsw_merlin_pytorch/Dockerfile.0.5.3
nvdsw/docker/nvdsw_merlin_pytorch/Dockerfile.0.6
nvdsw/docker/nvdsw_merlin_pytorch/Dockerfile.21.09
nvdsw/docker/nvdsw_merlin_pytorch/Dockerfile.21.12
nvdsw/docker/nvdsw_merlin_tf2/Dockerfile.0.5.3
nvdsw/docker/nvdsw_merlin_tf2/Dockerfile.0.6
nvdsw/docker/nvdsw_merlin_tf2/Dockerfile.21.09
nvdsw/docker/nvdsw_merlin_tf2/Dockerfile.21.12
nvdsw/docker/nvdsw_nemo/Dockerfile.1.1.0
nvdsw/docker/nvdsw_nemo/Dockerfile.1.2.0
nvdsw/docker/nvdsw_nemo/Dockerfile.1.3.0
nvdsw/docker/nvdsw_nemo/Dockerfile.1.4.0
nvdsw/docker/nvdsw_pl/Dockerfile.1.3.8
nvdsw/docker/nvdsw_pl/Dockerfile.1.4.0
nvdsw/docker/nvdsw_pytorch/Dockerfile.21.07
nvdsw/docker/nvdsw_pytorch/Dockerfile.21.08
nvdsw/docker/nvdsw_pytorch/Dockerfile.21.09
nvdsw/docker/nvdsw_pytorch/Dockerfile.21.10
nvdsw/docker/nvdsw_pytorch/Dockerfile.21.11
nvdsw/docker/nvdsw_rapids/Dockerfile.21.08
nvdsw/docker/nvdsw_rapids/Dockerfile.21.10
nvdsw/docker/nvdsw_spark/Dockerfile.3.1.2
nvdsw/docker/nvdsw_tf1/Dockerfile.21.07
nvdsw/docker/nvdsw_tf1/Dockerfile.21.08
nvdsw/docker/nvdsw_tf1/Dockerfile.21.09
nvdsw/docker/nvdsw_tf1/Dockerfile.21.10
nvdsw/docker/nvdsw_tf1/Dockerfile.21.11
nvdsw/docker/nvdsw_tf2/Dockerfile.21.07
nvdsw/docker/nvdsw_tf2/Dockerfile.21.08
nvdsw/docker/nvdsw_tf2/Dockerfile.21.09
nvdsw/docker/nvdsw_tf2/Dockerfile.21.10
nvdsw/docker/nvdsw_tf2/Dockerfile.21.11
nvdsw/images/account.svg
nvdsw-0.0.395.dist-info/METADATA
nvdsw-0.0.395.dist-info/WHEEL
nvdsw-0.0.395.dist-info/top_level.txt
nvdsw-0.0.395.dist-info/RECORD
