Metadata-Version: 2.1
Name: nvdsw
Version: 0.0.395
Summary: Nvidia Data Science Workbench
Home-page: http://www.nvidia.com/workbench
Author: Dima Rekesh
Author-email: drekesh@nvidia.com
License: UNKNOWN
Project-URL: Bug Tracker, https://github.com/NVIDIA/data-science-stack/issues
Platform: UNKNOWN
Classifier: Programming Language :: Python :: 3
Classifier: License :: Other/Proprietary License
Classifier: Operating System :: POSIX :: Linux
Requires-Python: >=3.6.9
Requires-Dist: pip (>=21.1.3)
Requires-Dist: PyYAML
Requires-Dist: feedparser
Requires-Dist: semver
Requires-Dist: pynvml
Requires-Dist: kaggle
Requires-Dist: jupyter-repo2docker
Requires-Dist: ewmh
Requires-Dist: timeago
Requires-Dist: iso8601
